LICENSE
MANIFEST.in
README.md
_build_utils.py
pyproject.toml
requirements.txt
static_yoga/__init__.py
static_yoga/__version__.py
static_yoga/color.py
static_yoga/primitives.py
static_yoga/py.typed
static_yoga/renderer.py
static_yoga/utils.py
static_yoga/widget.py
static_yoga.egg-info/PKG-INFO
static_yoga.egg-info/SOURCES.txt
static_yoga.egg-info/dependency_links.txt
static_yoga.egg-info/requires.txt
static_yoga.egg-info/top_level.txt
static_yoga/yoga/__init__.py
static_yoga/yoga/bridge.pxd
static_yoga/yoga/bridge.pyx
static_yoga/yoga/interfaces.py
static_yoga/yoga/yoga/CMakeLists.txt
static_yoga/yoga/yoga/yoga/BitUtils.h
static_yoga/yoga/yoga/yoga/CompactValue.h
static_yoga/yoga/yoga/yoga/Utils.cpp
static_yoga/yoga/yoga/yoga/Utils.h
static_yoga/yoga/yoga/yoga/YGConfig.cpp
static_yoga/yoga/yoga/yoga/YGConfig.h
static_yoga/yoga/yoga/yoga/YGEnums.cpp
static_yoga/yoga/yoga/yoga/YGEnums.h
static_yoga/yoga/yoga/yoga/YGFloatOptional.h
static_yoga/yoga/yoga/yoga/YGLayout.cpp
static_yoga/yoga/yoga/yoga/YGLayout.h
static_yoga/yoga/yoga/yoga/YGMacros.h
static_yoga/yoga/yoga/yoga/YGNode.cpp
static_yoga/yoga/yoga/yoga/YGNode.h
static_yoga/yoga/yoga/yoga/YGNodePrint.cpp
static_yoga/yoga/yoga/yoga/YGNodePrint.h
static_yoga/yoga/yoga/yoga/YGStyle.cpp
static_yoga/yoga/yoga/yoga/YGStyle.h
static_yoga/yoga/yoga/yoga/YGValue.cpp
static_yoga/yoga/yoga/yoga/YGValue.h
static_yoga/yoga/yoga/yoga/Yoga-internal.h
static_yoga/yoga/yoga/yoga/Yoga.cpp
static_yoga/yoga/yoga/yoga/Yoga.h
static_yoga/yoga/yoga/yoga/log.cpp
static_yoga/yoga/yoga/yoga/log.h
static_yoga/yoga/yoga/yoga/event/event.cpp
static_yoga/yoga/yoga/yoga/event/event.h
static_yoga/yoga/yoga/yoga/internal/experiments-inl.h
static_yoga/yoga/yoga/yoga/internal/experiments.cpp
static_yoga/yoga/yoga/yoga/internal/experiments.h
tests/test_yoga.py