Metadata-Version: 2.1
Name: static-yoga
Version: 0.1.0
Summary: Define and draw static layouts
Author-email: maxme1 <max@ira-labs.com>
License:                                  Apache License
Keywords: layout,rendering,drawing,widgets
Classifier: Development Status :: 5 - Production/Stable
Classifier: License :: OSI Approved :: Apache Software License
Classifier: Programming Language :: Python :: 3.10
Classifier: Programming Language :: Python :: 3.11
Requires-Python: >=3.10
License-File: LICENSE
Requires-Dist: numpy<2.0.0,>=1.11.0
Requires-Dist: pydantic<2.0.0
Requires-Dist: pyvips
Requires-Dist: drawSvg<2.0.0,>=1.0.0
Requires-Dist: multimethod<2.0.0,>=1.9.1
